cayennelpp/__init__.py
cayennelpp/lpp_data.py
cayennelpp/lpp_frame.py
cayennelpp/lpp_type.py
cayennelpp/lpp_util.py
pycayennelpp-2.3.0.dist-info/LICENSE
pycayennelpp-2.3.0.dist-info/METADATA
pycayennelpp-2.3.0.dist-info/WHEEL
pycayennelpp-2.3.0.dist-info/top_level.txt
pycayennelpp-2.3.0.dist-info/RECORD
