Metadata-Version: 2.1
Name: pycayennelpp
Version: 2.3.0
Summary: Encoder and Decoder for CayenneLLP
Home-page: http://github.com/smlng/pycayennelpp
Author: smlng
Author-email: s@mlng.net
License: MIT
Keywords: cayenne lpp iot lora lorawan ttn
Platform: UNKNOWN
Classifier: Development Status :: 5 - Production/Stable
Classifier: Intended Audience :: Developers
Classifier: License :: OSI Approved :: MIT License
Classifier: Operating System :: OS Independent
Classifier: Programming Language :: Python :: 3 :: Only
Classifier: Programming Language :: Python :: 3.6
Classifier: Programming Language :: Python :: 3.7
Classifier: Programming Language :: Python :: 3.8
Classifier: Programming Language :: Python :: 3.9
Requires-Python: >=3.6
